exaaiagnt/__init__.py
exaaiagnt/agents/ExaaiAgent/__init__.py
exaaiagnt/agents/ExaaiAgent/exaai_agent.py
exaaiagnt/agents/ExaaiAgent/system_prompt.jinja
exaaiagnt/agents/__init__.py
exaaiagnt/agents/agent_supervisor.py
exaaiagnt/agents/base_agent.py
exaaiagnt/agents/scan_modes.py
exaaiagnt/agents/shared_memory.py
exaaiagnt/agents/state.py
exaaiagnt/interface/__init__.py
exaaiagnt/interface/assets/tui_styles.tcss
exaaiagnt/interface/cli.py
exaaiagnt/interface/main.py
exaaiagnt/interface/tool_components/__init__.py
exaaiagnt/interface/tool_components/agents_graph_renderer.py
exaaiagnt/interface/tool_components/base_renderer.py
exaaiagnt/interface/tool_components/browser_renderer.py
exaaiagnt/interface/tool_components/file_edit_renderer.py
exaaiagnt/interface/tool_components/finish_renderer.py
exaaiagnt/interface/tool_components/notes_renderer.py
exaaiagnt/interface/tool_components/proxy_renderer.py
exaaiagnt/interface/tool_components/python_renderer.py
exaaiagnt/interface/tool_components/registry.py
exaaiagnt/interface/tool_components/reporting_renderer.py
exaaiagnt/interface/tool_components/scan_info_renderer.py
exaaiagnt/interface/tool_components/terminal_renderer.py
exaaiagnt/interface/tool_components/thinking_renderer.py
exaaiagnt/interface/tool_components/user_message_renderer.py
exaaiagnt/interface/tool_components/web_search_renderer.py
exaaiagnt/interface/tui.py
exaaiagnt/interface/utils.py
exaaiagnt/llm/__init__.py
exaaiagnt/llm/config.py
exaaiagnt/llm/fallback.py
exaaiagnt/llm/llm.py
exaaiagnt/llm/llm_traffic_controller.py
exaaiagnt/llm/memory_compressor.py
exaaiagnt/llm/output_processor.py
exaaiagnt/llm/request_queue.py
exaaiagnt/llm/utils.py
exaaiagnt/prompts/README.md
exaaiagnt/prompts/__init__.py
exaaiagnt/prompts/auto_loader.py
exaaiagnt/prompts/cloud/.gitkeep
exaaiagnt/prompts/cloud/aws_cloud_security.jinja
exaaiagnt/prompts/coordination/root_agent.jinja
exaaiagnt/prompts/custom/.gitkeep
exaaiagnt/prompts/frameworks/fastapi.jinja
exaai_agent-2.0.9.dist-info/METADATA
exaai_agent-2.0.9.dist-info/WHEEL
exaai_agent-2.0.9.dist-info/entry_points.txt
exaai_agent-2.0.9.dist-info/licenses/LICENSE
exaai_agent-2.0.9.dist-info/RECORD
