Metadata-Version: 2.4
Name: exaai-agent
Version: 2.0.9
Summary: ExaAi - Advanced AI Security Agent for Comprehensive Penetration Testing
License: Apache-2.0
License-File: LICENSE
Keywords: cybersecurity,security,vulnerability,scanner,pentest,agent,ai,cli
Author: ExaAi Team
Author-email: mahmedhleli@gmail.com
Requires-Python: >=3.12,<4.0
Classifier: Development Status :: 3 - Alpha
Classifier: Environment :: Console
Classifier: Intended Audience :: Information Technology
Classifier: Intended Audience :: System Administrators
Classifier: License :: OSI Approved :: Apache Software License
Classifier: Programming Language :: Python
Classifier: Programming Language :: Python :: 3
Classifier: Programming Language :: Python :: 3.12
Classifier: Programming Language :: Python :: 3.13
Classifier: Programming Language :: Python :: 3.14
Classifier: Programming Language :: Python :: 3 :: Only
Classifier: Topic :: Security
Requires-Dist: docker (>=7.1.0,<8.0.0)
Requires-Dist: fastapi
Requires-Dist: gql[requests] (>=3.5.3,<4.0.0)
Requires-Dist: ipython (>=9.3.0,<10.0.0)
Requires-Dist: libtmux (>=0.46.2,<0.47.0)
Requires-Dist: litellm[proxy] (>=1.79.1,<1.80.0)
Requires-Dist: numpydoc (>=1.8.0,<2.0.0)
Requires-Dist: openai (>=1.99.5,<1.100.0)
Requires-Dist: openhands-aci (>=0.3.0,<0.4.0)
Requires-Dist: playwright (>=1.48.0,<2.0.0)
Requires-Dist: pydantic[email] (>=2.11.3,<3.0.0)
Requires-Dist: pyte (>=0.8.1,<0.9.0)
Requires-Dist: requests (>=2.32.0,<3.0.0)
Requires-Dist: rich
Requires-Dist: tenacity (>=9.0.0,<10.0.0)
Requires-Dist: textual (>=4.0.0,<5.0.0)
Requires-Dist: uvicorn
Requires-Dist: xmltodict (>=0.13.0,<0.14.0)
